constants.py
redcoffee.py
styling.py
support.py
ascii_art/__init__.py
ascii_art/constants.py
ascii_art/welcome_banner.py
core/__init__.py
core/analyser.py
core/utils/__init__.py
core/utils/sonarqube_utils.py
diagnose/__init__.py
diagnose/constants.py
diagnose/sanity.py
integrations/__init__.py
integrations/ipinfo_integration.py
integrations/sentry_integration.py
reports/__init__.py
reports/templating.py
reports/utils/__init__.py
reports/utils/report_utils.py
utils/__init__.py
utils/general_utils.py
redcoffee-2.16.dist-info/LICENSE
redcoffee-2.16.dist-info/METADATA
redcoffee-2.16.dist-info/WHEEL
redcoffee-2.16.dist-info/entry_points.txt
redcoffee-2.16.dist-info/top_level.txt
redcoffee-2.16.dist-info/RECORD
