Metadata-Version: 2.1
Name: redcoffee
Version: 2.16
Summary: A command-line tool to generate PDF for SonarQube Reports
Author: Anubhav Sanyal
License-File: LICENSE
Requires-Dist: click
Requires-Dist: reportlab
Requires-Dist: pytest
Requires-Dist: requests
Requires-Dist: setuptools
Requires-Dist: ipinfo
Requires-Dist: sentry-sdk
Requires-Dist: python-dotenv
Requires-Dist: pyfiglet
Requires-Dist: colorama
